qpy/__init__.py
qpy/block.py
qpy/core.py
qpy/error.py
qpy/favorite.py
qpy/feed.py
qpy/follow.py
qpy/notification.py
qpy/user.py
qpost-1.0.0.dist-info/LICENSE
qpost-1.0.0.dist-info/METADATA
qpost-1.0.0.dist-info/WHEEL
qpost-1.0.0.dist-info/top_level.txt
qpost-1.0.0.dist-info/RECORD
