Metadata-Version: 2.1
Name: qpost
Version: 1.0.0
Summary: A basic qpost API wrapper
Home-page: https://github.com/medjedqt/qpost
Author: medjed
Author-email: imoshugi01@gmail.com
License: UNKNOWN
Platform: UNKNOWN
Classifier: Development Status :: 4 - Beta
Classifier: Operating System :: OS Independent
Classifier: Programming Language :: Python :: 3
Classifier: Topic :: Internet
Classifier: Topic :: Software Development :: Libraries
Classifier: Topic :: Software Development :: Libraries :: Python Modules
Classifier: Topic :: Utilities
Requires-Python: >=3.6
